json_beautifier/__init__.py
json_beautifier/cli.py
json_beautifier-0.1.1.dist-info/METADATA
json_beautifier-0.1.1.dist-info/WHEEL
json_beautifier-0.1.1.dist-info/entry_points.txt
json_beautifier-0.1.1.dist-info/top_level.txt
json_beautifier-0.1.1.dist-info/RECORD
