Metadata-Version: 2.4
Name: json-beautifier
Version: 0.1.1
Requires-Python: >=3.8
Requires-Dist: click>=8.1.8
Requires-Dist: pylint>=3.2.7
Requires-Dist: pytest>=8.3.5
